setup.py
distributions_GB_SA/Binomialdistribution.py
distributions_GB_SA/Gaussiandistribution.py
distributions_GB_SA/Generaldistribution.py
distributions_GB_SA/__init__.py
distributions_GB_SA.egg-info/PKG-INFO
distributions_GB_SA.egg-info/SOURCES.txt
distributions_GB_SA.egg-info/dependency_links.txt
distributions_GB_SA.egg-info/not-zip-safe
distributions_GB_SA.egg-info/top_level.txt