Metadata-Version: 1.0
Name: distributions-GB-SA
Version: 0.1
Summary: Gaussian and binomial distributions
Home-page: UNKNOWN
Author: SOUKAINA ABELHAD
Author-email: abelhad.soukaina@gmail.com
License: UNKNOWN
Platform: UNKNOWN
